winboost
