Metadata-Version: 2.1
Name: winboost
Version: 2.1
Summary: WinBoost: Boost your windows system
Home-page: https://github.com/cyborg7898/WinBoost
Author: Smit Parmar, Sanket Jethava, Dhiraj Beri
Author-email: smitraj333@gmail.com, sanketjethava@gmail.com, dhirajberi.official@gmail.com
License: MIT
Download-URL: https://github.com/cyborg7898/WinBoost/archive/refs/tags/2.1.tar.gz
Keywords: windows,boost,optimize,window 10,os,temp cleaner,cleanup,cache cleaner
Platform: UNKNOWN
Classifier: Development Status :: 5 - Production/Stable
Classifier: Intended Audience :: Developers
Classifier: Topic :: Software Development :: Build Tools
Classifier: License :: OSI Approved :: MIT License
Classifier: Programming Language :: Python :: 3
Classifier: Programming Language :: Python :: 3.4
Classifier: Programming Language :: Python :: 3.5
Classifier: Programming Language :: Python :: 3.6
Classifier: Programming Language :: Python :: 3.7
Classifier: Programming Language :: Python :: 3.8
